<?xml version="1.0" encoding="UTF-8" ?>
<!DOCTYPE mapper PUBLIC "-//mybatis.org//DTD Mapper 3.0//EN" "http://mybatis.org/dtd/mybatis-3-mapper.dtd" >
<mapper namespace="com.spring.web.dao.TRecheckMapper" >
  <resultMap id="BaseResultMap" type="com.spring.web.model.TRecheck" >
    <!--
      WARNING - @mbggenerated
      This element is automatically generated by MyBatis Generator, do not modify.
    -->
    <constructor >
      <idArg column="id" jdbcType="INTEGER" javaType="java.lang.Integer" />
      <arg column="check_id" jdbcType="INTEGER" javaType="java.lang.Integer" />
      <arg column="user_id" jdbcType="INTEGER" javaType="java.lang.Integer" />
      <arg column="create_user" jdbcType="INTEGER" javaType="java.lang.Integer" />
      <arg column="status" jdbcType="INTEGER" javaType="java.lang.Integer" />
      <arg column="create_time" jdbcType="TIMESTAMP" javaType="java.util.Date" />
      <arg column="next_time" jdbcType="TIMESTAMP" javaType="java.util.Date" />
      <arg column="checker" jdbcType="VARCHAR" javaType="java.lang.String" />
      <arg column="check_company" jdbcType="VARCHAR" javaType="java.lang.String" />
      <arg column="dapart_contact" jdbcType="VARCHAR" javaType="java.lang.String" />
    </constructor>
  </resultMap>
  <sql id="Base_Column_List" >
    <!--
      WARNING - @mbggenerated
      This element is automatically generated by MyBatis Generator, do not modify.
    -->
    id, check_id, user_id, create_user, status, create_time, next_time, checker, check_company, 
    dapart_contact
  </sql>
  <select id="selectByPrimaryKey" resultMap="BaseResultMap" parameterType="java.lang.Integer" >
    <!--
      WARNING - @mbggenerated
      This element is automatically generated by MyBatis Generator, do not modify.
    -->
    select 
    <include refid="Base_Column_List" />
    from t_recheck_tbl
    where id = #{id,jdbcType=INTEGER}
  </select>
  <delete id="deleteByPrimaryKey" parameterType="java.lang.Integer" >
    <!--
      WARNING - @mbggenerated
      This element is automatically generated by MyBatis Generator, do not modify.
    -->
    delete from t_recheck_tbl
    where id = #{id,jdbcType=INTEGER}
  </delete>
  <insert id="insert" parameterType="com.spring.web.model.TRecheck" >
    <!--
      WARNING - @mbggenerated
      This element is automatically generated by MyBatis Generator, do not modify.
    -->
    <selectKey resultType="java.lang.Integer" keyProperty="id" order="AFTER" >
      SELECT LAST_INSERT_ID()
    </selectKey>
    insert into t_recheck_tbl (check_id, user_id, create_user, 
      status, create_time, next_time, 
      checker, check_company, dapart_contact
      )
    values (#{checkId,jdbcType=INTEGER}, #{userId,jdbcType=INTEGER}, #{createUser,jdbcType=INTEGER}, 
      #{status,jdbcType=INTEGER}, #{createTime,jdbcType=TIMESTAMP}, #{nextTime,jdbcType=TIMESTAMP}, 
      #{checker,jdbcType=VARCHAR}, #{checkCompany,jdbcType=VARCHAR}, #{dapartContact,jdbcType=VARCHAR}
      )
  </insert>
  <insert id="insertSelective" parameterType="com.spring.web.model.TRecheck" >
    <!--
      WARNING - @mbggenerated
      This element is automatically generated by MyBatis Generator, do not modify.
    -->
    <selectKey resultType="java.lang.Integer" keyProperty="id" order="AFTER" >
      SELECT LAST_INSERT_ID()
    </selectKey>
    insert into t_recheck_tbl
    <trim prefix="(" suffix=")" suffixOverrides="," >
      <if test="checkId != null" >
        check_id,
      </if>
      <if test="userId != null" >
        user_id,
      </if>
      <if test="createUser != null" >
        create_user,
      </if>
      <if test="status != null" >
        status,
      </if>
      <if test="createTime != null" >
        create_time,
      </if>
      <if test="nextTime != null" >
        next_time,
      </if>
      <if test="checker != null" >
        checker,
      </if>
      <if test="checkCompany != null" >
        check_company,
      </if>
      <if test="dapartContact != null" >
        dapart_contact,
      </if>
    </trim>
    <trim prefix="values (" suffix=")" suffixOverrides="," >
      <if test="checkId != null" >
        #{checkId,jdbcType=INTEGER},
      </if>
      <if test="userId != null" >
        #{userId,jdbcType=INTEGER},
      </if>
      <if test="createUser != null" >
        #{createUser,jdbcType=INTEGER},
      </if>
      <if test="status != null" >
        #{status,jdbcType=INTEGER},
      </if>
      <if test="createTime != null" >
        #{createTime,jdbcType=TIMESTAMP},
      </if>
      <if test="nextTime != null" >
        #{nextTime,jdbcType=TIMESTAMP},
      </if>
      <if test="checker != null" >
        #{checker,jdbcType=VARCHAR},
      </if>
      <if test="checkCompany != null" >
        #{checkCompany,jdbcType=VARCHAR},
      </if>
      <if test="dapartContact != null" >
        #{dapartContact,jdbcType=VARCHAR},
      </if>
    </trim>
  </insert>
  <update id="updateByPrimaryKeySelective" parameterType="com.spring.web.model.TRecheck" >
    <!--
      WARNING - @mbggenerated
      This element is automatically generated by MyBatis Generator, do not modify.
    -->
    update t_recheck_tbl
    <set >
      <if test="checkId != null" >
        check_id = #{checkId,jdbcType=INTEGER},
      </if>
      <if test="userId != null" >
        user_id = #{userId,jdbcType=INTEGER},
      </if>
      <if test="createUser != null" >
        create_user = #{createUser,jdbcType=INTEGER},
      </if>
      <if test="status != null" >
        status = #{status,jdbcType=INTEGER},
      </if>
      <if test="createTime != null" >
        create_time = #{createTime,jdbcType=TIMESTAMP},
      </if>
      <if test="nextTime != null" >
        next_time = #{nextTime,jdbcType=TIMESTAMP},
      </if>
      <if test="checker != null" >
        checker = #{checker,jdbcType=VARCHAR},
      </if>
      <if test="checkCompany != null" >
        check_company = #{checkCompany,jdbcType=VARCHAR},
      </if>
      <if test="dapartContact != null" >
        dapart_contact = #{dapartContact,jdbcType=VARCHAR},
      </if>
    </set>
    where id = #{id,jdbcType=INTEGER}
  </update>
  <update id="updateByPrimaryKey" parameterType="com.spring.web.model.TRecheck" >
    <!--
      WARNING - @mbggenerated
      This element is automatically generated by MyBatis Generator, do not modify.
    -->
    update t_recheck_tbl
    set check_id = #{checkId,jdbcType=INTEGER},
      user_id = #{userId,jdbcType=INTEGER},
      create_user = #{createUser,jdbcType=INTEGER},
      status = #{status,jdbcType=INTEGER},
      create_time = #{createTime,jdbcType=TIMESTAMP},
      next_time = #{nextTime,jdbcType=TIMESTAMP},
      checker = #{checker,jdbcType=VARCHAR},
      check_company = #{checkCompany,jdbcType=VARCHAR},
      dapart_contact = #{dapartContact,jdbcType=VARCHAR}
    where id = #{id,jdbcType=INTEGER}
  </update>


   <select id="selectByCheckId" resultMap="BaseResultMap" parameterType="java.lang.Integer" >
    select 
    <include refid="Base_Column_List" />
    from t_recheck_tbl
    where check_id = #{checkId}
    order by id desc
  </select>
</mapper>